test/test_losses/__init__.py
test/test_losses/test_cluster_loss.py
test/test_losses/test_sparsity_loss.py
torch_deeptype/__init__.py
torch_deeptype/deeptype_model.py
torch_deeptype/deeptype_trainer.py
torch_deeptype/losses.py
torch_deeptype-0.1.2.dist-info/METADATA
torch_deeptype-0.1.2.dist-info/WHEEL
torch_deeptype-0.1.2.dist-info/top_level.txt
torch_deeptype-0.1.2.dist-info/RECORD
