Metadata-Version: 2.1
Name: torch-deeptype
Version: 0.1.2
Summary: PyTorch implementation of DeepType with clustering and sparsity
Home-page: https://github.com/physboom/torch-deeptype
Author: Matthew Chak
Author-email: mchak@calpoly.edu
Classifier: Development Status :: 3 - Alpha
Classifier: Intended Audience :: Science/Research
Classifier: Programming Language :: Python :: 3
Classifier: License :: OSI Approved :: MIT License
Classifier: Operating System :: OS Independent
Requires-Python: >=3.7
Requires-Dist: torch
Requires-Dist: scikit-learn
Requires-Dist: numpy
